cep/__init__.py
cep/client.py
cep/cuenta.py
cep/transferencia.py
cep/version.py
tests/__init__.py
tests/conftest.py
tests/test_client.py
tests/test_transferencia.py
cepmex_bp-0.1.9.dist-info/LICENSE
cepmex_bp-0.1.9.dist-info/METADATA
cepmex_bp-0.1.9.dist-info/WHEEL
cepmex_bp-0.1.9.dist-info/top_level.txt
cepmex_bp-0.1.9.dist-info/RECORD
