Metadata-Version: 2.1
Name: cepmex-bp
Version: 0.1.9
Summary: CEP client library
Home-page: https://github.com/lucf25/cep-python
Author: BanPAY
Author-email: dev@banpay.com
License: UNKNOWN
Platform: UNKNOWN
Classifier: Programming Language :: Python :: 3.7
Classifier: License :: OSI Approved :: MIT License
Classifier: Operating System :: OS Independent
Requires-Python: >=3.7
License-File: LICENSE
Requires-Dist: requests (<2.26,>=2.25)
Requires-Dist: clabe-bp (<1.3,>=1.2.4)
Requires-Dist: lxml (<4.7,>=4.6.2)
Requires-Dist: dataclasses (>=0.6) ; python_version < "3.7"
